{
  "lastUpdated": "2026-06-25T16:22:02.279Z",
  "summary": {
    "totalPages": 26,
    "analyzed": 26,
    "failed": 0,
    "averagePerformance": 94,
    "stressTest": {
      "simulatedUsers": 5000,
      "methodology": "Logarithmic Load Degradation (SRE 2026)",
      "globalResilienceScore": 86,
      "status": "STABLE / HIGH_AVAILABILITY"
    }
  },
  "pages": [
    {
      "url": "https://gitechnolo.github.io/biotechproject/index.html",
      "label": "Homepage",
      "slug": "index",
      "category": "biotecnologie",
      "performanceScore": 99,
      "loadTime": 1778,
      "firstPaint": 1420,
      "lastAnalyzed": "2026-06-25T16:17:15.470Z",
      "stressResilienceScore": 90,
      "previousPerformanceScore": 68
    },
    {
      "url": "https://gitechnolo.github.io/biotechproject/Cuore.html",
      "label": "Cuore",
      "slug": "cuore",
      "category": "fisiologia",
      "performanceScore": 98,
      "loadTime": 2344,
      "firstPaint": 1085,
      "lastAnalyzed": "2026-06-25T16:17:26.309Z",
      "stressResilienceScore": 89,
      "previousPerformanceScore": 97
    },
    {
      "url": "https://gitechnolo.github.io/biotechproject/Cuore-semplice.html",
      "label": "Cuore (versione semplificata)",
      "slug": "cuore-semplice",
      "category": "accessibilità",
      "performanceScore": 96,
      "loadTime": 2721,
      "firstPaint": 1537,
      "lastAnalyzed": "2026-06-25T16:17:37.881Z",
      "stressResilienceScore": 87,
      "previousPerformanceScore": 93
    },
    {
      "url": "https://gitechnolo.github.io/biotechproject/Apparato_respiratorio.html",
      "label": "Apparato respiratorio",
      "slug": "apparato-respiratorio",
      "category": "fisiologia",
      "performanceScore": 93,
      "loadTime": 1089,
      "firstPaint": 939,
      "lastAnalyzed": "2026-06-25T16:17:50.256Z",
      "stressResilienceScore": 85,
      "previousPerformanceScore": 83
    },
    {
      "url": "https://gitechnolo.github.io/biotechproject/Apparato_respiratorio-semplice.html",
      "label": "Apparato respiratorio (versione semplificata)",
      "slug": "apparato-respiratorio-semplice",
      "category": "accessibilità",
      "performanceScore": 81,
      "loadTime": 3979,
      "firstPaint": 923,
      "lastAnalyzed": "2026-06-25T16:18:01.856Z",
      "stressResilienceScore": 74,
      "previousPerformanceScore": 82
    },
    {
      "url": "https://gitechnolo.github.io/biotechproject/Apparato_digerente.html",
      "label": "Apparato digerente",
      "slug": "apparato-digerente",
      "category": "fisiologia",
      "performanceScore": 91,
      "loadTime": 3394,
      "firstPaint": 1385,
      "lastAnalyzed": "2026-06-25T16:18:13.670Z",
      "stressResilienceScore": 83,
      "previousPerformanceScore": 90
    },
    {
      "url": "https://gitechnolo.github.io/biotechproject/Apparato_digerente-semplice.html",
      "label": "Apparato digerente (versione semplificata)",
      "slug": "apparato-digerente-semplice",
      "category": "accessibilità",
      "performanceScore": 83,
      "loadTime": 4578,
      "firstPaint": 1710,
      "lastAnalyzed": "2026-06-25T16:18:25.782Z",
      "stressResilienceScore": 76,
      "previousPerformanceScore": 89
    },
    {
      "url": "https://gitechnolo.github.io/biotechproject/Apparato_tegumentario.html",
      "label": "Apparato tegumentario",
      "slug": "apparato-tegumentario",
      "category": "fisiologia",
      "performanceScore": 98,
      "loadTime": 2403,
      "firstPaint": 1237,
      "lastAnalyzed": "2026-06-25T16:18:37.867Z",
      "stressResilienceScore": 89,
      "previousPerformanceScore": 99
    },
    {
      "url": "https://gitechnolo.github.io/biotechproject/Apparato_tegumentario-semplice.html",
      "label": "Apparato tegumentario (versione semplificata)",
      "slug": "apparato-tegumentario-semplice",
      "category": "accessibilità",
      "performanceScore": 95,
      "loadTime": 1484,
      "firstPaint": 937,
      "lastAnalyzed": "2026-06-25T16:18:50.323Z",
      "stressResilienceScore": 86,
      "previousPerformanceScore": 93
    },
    {
      "url": "https://gitechnolo.github.io/biotechproject/Sistema_linfatico.html",
      "label": "Sistema linfatico",
      "slug": "sistema-linfatico",
      "category": "fisiologia",
      "performanceScore": 98,
      "loadTime": 2255,
      "firstPaint": 1104,
      "lastAnalyzed": "2026-06-25T16:19:01.319Z",
      "stressResilienceScore": 89,
      "previousPerformanceScore": 98
    },
    {
      "url": "https://gitechnolo.github.io/biotechproject/Sistema_linfatico-semplice.html",
      "label": "Sistema linfatico (versione semplificata)",
      "slug": "sistema-linfatico-semplice",
      "category": "accessibilità",
      "performanceScore": 96,
      "loadTime": 2650,
      "firstPaint": 1546,
      "lastAnalyzed": "2026-06-25T16:19:12.302Z",
      "stressResilienceScore": 87,
      "previousPerformanceScore": 94
    },
    {
      "url": "https://gitechnolo.github.io/biotechproject/Dermatologia.html",
      "label": "Dermatologia",
      "slug": "dermatologia",
      "category": "fisiologia",
      "performanceScore": 93,
      "loadTime": 1159,
      "firstPaint": 934,
      "lastAnalyzed": "2026-06-25T16:19:24.358Z",
      "stressResilienceScore": 85,
      "previousPerformanceScore": 99
    },
    {
      "url": "https://gitechnolo.github.io/biotechproject/Dermatologia-semplice.html",
      "label": "Dermatologia (versione semplificata)",
      "slug": "dermatologia-semplice",
      "category": "accessibilità",
      "performanceScore": 97,
      "loadTime": 1436,
      "firstPaint": 986,
      "lastAnalyzed": "2026-06-25T16:19:36.086Z",
      "stressResilienceScore": 88,
      "previousPerformanceScore": 92
    },
    {
      "url": "https://gitechnolo.github.io/biotechproject/Cellula.html",
      "label": "Cellula",
      "slug": "cellula",
      "category": "fisiologia",
      "performanceScore": 93,
      "loadTime": 3154,
      "firstPaint": 1271,
      "lastAnalyzed": "2026-06-25T16:19:47.980Z",
      "stressResilienceScore": 85,
      "previousPerformanceScore": 89
    },
    {
      "url": "https://gitechnolo.github.io/biotechproject/Cellula-semplice.html",
      "label": "Cellula (versione semplificata)",
      "slug": "cellula-semplice",
      "category": "accessibilità",
      "performanceScore": 91,
      "loadTime": 3468,
      "firstPaint": 1532,
      "lastAnalyzed": "2026-06-25T16:19:58.673Z",
      "stressResilienceScore": 83,
      "previousPerformanceScore": 87
    },
    {
      "url": "https://gitechnolo.github.io/biotechproject/Capelli.html",
      "label": "Capelli",
      "slug": "capelli",
      "category": "fisiologia",
      "performanceScore": 98,
      "loadTime": 2101,
      "firstPaint": 1501,
      "lastAnalyzed": "2026-06-25T16:20:11.459Z",
      "stressResilienceScore": 89,
      "previousPerformanceScore": 93
    },
    {
      "url": "https://gitechnolo.github.io/biotechproject/Capelli-semplice.html",
      "label": "Capelli (versione semplificata)",
      "slug": "capelli-semplice",
      "category": "accessibilità",
      "performanceScore": 98,
      "loadTime": 2148,
      "firstPaint": 1534,
      "lastAnalyzed": "2026-06-25T16:20:22.319Z",
      "stressResilienceScore": 89,
      "previousPerformanceScore": 94
    },
    {
      "url": "https://gitechnolo.github.io/biotechproject/Staff.html",
      "label": "Staff",
      "slug": "staff",
      "category": "staff",
      "performanceScore": 100,
      "loadTime": 1912,
      "firstPaint": 1053,
      "lastAnalyzed": "2026-06-25T16:20:33.052Z",
      "stressResilienceScore": 91,
      "previousPerformanceScore": 100
    },
    {
      "url": "https://gitechnolo.github.io/biotechproject/Progetti.html",
      "label": "Progetti",
      "slug": "progetti",
      "category": "altro",
      "performanceScore": 100,
      "loadTime": 1789,
      "firstPaint": 1054,
      "lastAnalyzed": "2026-06-25T16:20:43.787Z",
      "stressResilienceScore": 91,
      "previousPerformanceScore": 99
    },
    {
      "url": "https://gitechnolo.github.io/biotechproject/Marketing.html",
      "label": "Marketing",
      "slug": "marketing",
      "category": "mercato cibernetica",
      "performanceScore": 100,
      "loadTime": 1728,
      "firstPaint": 1053,
      "lastAnalyzed": "2026-06-25T16:20:55.886Z",
      "stressResilienceScore": 91,
      "previousPerformanceScore": 79
    },
    {
      "url": "https://gitechnolo.github.io/biotechproject/O.S_support.html",
      "label": "Supporto OS",
      "slug": "os-support",
      "category": "supporto",
      "performanceScore": 99,
      "loadTime": 1803,
      "firstPaint": 1535,
      "lastAnalyzed": "2026-06-25T16:21:05.181Z",
      "stressResilienceScore": 90,
      "previousPerformanceScore": 99
    },
    {
      "url": "https://gitechnolo.github.io/biotechproject/Tablet_forum.html",
      "label": "Forum Tablet",
      "slug": "tablet-forum",
      "category": "forum",
      "performanceScore": 87,
      "loadTime": 908,
      "firstPaint": 758,
      "lastAnalyzed": "2026-06-25T16:21:14.218Z",
      "stressResilienceScore": 79,
      "previousPerformanceScore": 87
    },
    {
      "url": "https://gitechnolo.github.io/biotechproject/Specials.html",
      "label": "Specials",
      "slug": "specials",
      "category": "cellule staminali robotica",
      "performanceScore": 99,
      "loadTime": 2043,
      "firstPaint": 1130,
      "lastAnalyzed": "2026-06-25T16:21:24.842Z",
      "stressResilienceScore": 90,
      "previousPerformanceScore": 99
    },
    {
      "url": "https://gitechnolo.github.io/biotechproject/Tech_Maturity.html",
      "label": "Maturità tecnologica",
      "slug": "tech-maturity",
      "category": "maturità tecnologica",
      "performanceScore": 92,
      "loadTime": 1812,
      "firstPaint": 756,
      "lastAnalyzed": "2026-06-25T16:21:37.929Z",
      "stressResilienceScore": 84,
      "previousPerformanceScore": 88
    },
    {
      "url": "https://gitechnolo.github.io/biotechproject/accessibility-it.html",
      "label": "Accessibilità (informazioni)",
      "slug": "accessibility-it",
      "category": "accessibilità",
      "performanceScore": 79,
      "loadTime": 1503,
      "firstPaint": 1102,
      "lastAnalyzed": "2026-06-25T16:21:48.861Z",
      "stressResilienceScore": 72,
      "previousPerformanceScore": 99
    },
    {
      "url": "https://gitechnolo.github.io/biotechproject/accessibility-en.html",
      "label": "Accessibility (information)",
      "slug": "accessibility-en",
      "category": "accessibilità",
      "performanceScore": 99,
      "loadTime": 2021,
      "firstPaint": 1259,
      "lastAnalyzed": "2026-06-25T16:21:59.249Z",
      "stressResilienceScore": 90,
      "previousPerformanceScore": 99
    }
  ]
}