{
  "lastUpdated": "2025-12-09T11:18:02.944Z",
  "summary": {
    "totalPages": 26,
    "analyzed": 26,
    "failed": 0,
    "averagePerformance": 97
  },
  "pages": [
    {
      "url": "https://gitechnolo.github.io/biotechproject/index.html",
      "label": "Homepage",
      "slug": "index",
      "category": "biotecnologie",
      "performanceScore": 92,
      "loadTime": 1260,
      "firstPaint": 1260,
      "lastAnalyzed": "2025-12-09T11:09:03.453Z",
      "previousPerformanceScore": 90
    },
    {
      "url": "https://gitechnolo.github.io/biotechproject/Cuore.html",
      "label": "Cuore",
      "slug": "cuore",
      "category": "fisiologia",
      "performanceScore": 100,
      "loadTime": 508,
      "firstPaint": 508,
      "lastAnalyzed": "2025-12-09T11:09:24.571Z",
      "previousPerformanceScore": 100
    },
    {
      "url": "https://gitechnolo.github.io/biotechproject/Cuore-semplice.html",
      "label": "Cuore (versione semplificata)",
      "slug": "cuore-semplice",
      "category": "accessibilità",
      "performanceScore": 100,
      "loadTime": 448,
      "firstPaint": 448,
      "lastAnalyzed": "2025-12-09T11:09:46.439Z",
      "previousPerformanceScore": 100
    },
    {
      "url": "https://gitechnolo.github.io/biotechproject/Apparato_respiratorio.html",
      "label": "Apparato respiratorio",
      "slug": "apparato-respiratorio",
      "category": "fisiologia",
      "performanceScore": 100,
      "loadTime": 485,
      "firstPaint": 382,
      "lastAnalyzed": "2025-12-09T11:10:07.883Z",
      "previousPerformanceScore": 100
    },
    {
      "url": "https://gitechnolo.github.io/biotechproject/Apparato_respiratorio-semplice.html",
      "label": "Apparato respiratorio (versione semplificata)",
      "slug": "apparato-respiratorio-semplice",
      "category": "accessibilità",
      "performanceScore": 100,
      "loadTime": 377,
      "firstPaint": 377,
      "lastAnalyzed": "2025-12-09T11:10:29.618Z",
      "previousPerformanceScore": 100
    },
    {
      "url": "https://gitechnolo.github.io/biotechproject/Apparato_digerente.html",
      "label": "Apparato digerente",
      "slug": "apparato-digerente",
      "category": "fisiologia",
      "performanceScore": 94,
      "loadTime": 580,
      "firstPaint": 580,
      "lastAnalyzed": "2025-12-09T11:10:51.732Z",
      "previousPerformanceScore": 97
    },
    {
      "url": "https://gitechnolo.github.io/biotechproject/Apparato_digerente-semplice.html",
      "label": "Apparato digerente (versione semplificata)",
      "slug": "apparato-digerente-semplice",
      "category": "accessibilità",
      "performanceScore": 92,
      "loadTime": 691,
      "firstPaint": 378,
      "lastAnalyzed": "2025-12-09T11:11:15.278Z",
      "previousPerformanceScore": 92
    },
    {
      "url": "https://gitechnolo.github.io/biotechproject/Apparato_tegumentario.html",
      "label": "Apparato tegumentario",
      "slug": "apparato-tegumentario",
      "category": "fisiologia",
      "performanceScore": 100,
      "loadTime": 352,
      "firstPaint": 352,
      "lastAnalyzed": "2025-12-09T11:11:38.888Z",
      "previousPerformanceScore": 98
    },
    {
      "url": "https://gitechnolo.github.io/biotechproject/Apparato_tegumentario-semplice.html",
      "label": "Apparato tegumentario (versione semplificata)",
      "slug": "apparato-tegumentario-semplice",
      "category": "accessibilità",
      "performanceScore": 89,
      "loadTime": 390,
      "firstPaint": 390,
      "lastAnalyzed": "2025-12-09T11:12:02.848Z",
      "previousPerformanceScore": 89
    },
    {
      "url": "https://gitechnolo.github.io/biotechproject/Sistema_linfatico.html",
      "label": "Sistema linfatico",
      "slug": "sistema-linfatico",
      "category": "fisiologia",
      "performanceScore": 100,
      "loadTime": 488,
      "firstPaint": 488,
      "lastAnalyzed": "2025-12-09T11:12:23.936Z",
      "previousPerformanceScore": 100
    },
    {
      "url": "https://gitechnolo.github.io/biotechproject/Sistema_linfatico-semplice.html",
      "label": "Sistema linfatico (versione semplificata)",
      "slug": "sistema-linfatico-semplice",
      "category": "accessibilità",
      "performanceScore": 100,
      "loadTime": 433,
      "firstPaint": 433,
      "lastAnalyzed": "2025-12-09T11:12:45.780Z",
      "previousPerformanceScore": 100
    },
    {
      "url": "https://gitechnolo.github.io/biotechproject/Dermatologia.html",
      "label": "Dermatologia",
      "slug": "dermatologia",
      "category": "fisiologia",
      "performanceScore": 100,
      "loadTime": 340,
      "firstPaint": 340,
      "lastAnalyzed": "2025-12-09T11:13:07.186Z",
      "previousPerformanceScore": 100
    },
    {
      "url": "https://gitechnolo.github.io/biotechproject/Dermatologia-semplice.html",
      "label": "Dermatologia (versione semplificata)",
      "slug": "dermatologia-semplice",
      "category": "accessibilità",
      "performanceScore": 89,
      "loadTime": 428,
      "firstPaint": 335,
      "lastAnalyzed": "2025-12-09T11:13:29.795Z",
      "previousPerformanceScore": 100
    },
    {
      "url": "https://gitechnolo.github.io/biotechproject/Cellula.html",
      "label": "Cellula",
      "slug": "cellula",
      "category": "fisiologia",
      "performanceScore": 95,
      "loadTime": 1134,
      "firstPaint": 377,
      "lastAnalyzed": "2025-12-09T11:13:52.252Z",
      "previousPerformanceScore": 93
    },
    {
      "url": "https://gitechnolo.github.io/biotechproject/Cellula-semplice.html",
      "label": "Cellula (versione semplificata)",
      "slug": "cellula-semplice",
      "category": "accessibilità",
      "performanceScore": 100,
      "loadTime": 380,
      "firstPaint": 380,
      "lastAnalyzed": "2025-12-09T11:14:13.494Z",
      "previousPerformanceScore": 100
    },
    {
      "url": "https://gitechnolo.github.io/biotechproject/Capelli.html",
      "label": "Capelli",
      "slug": "capelli",
      "category": "fisiologia",
      "performanceScore": 85,
      "loadTime": 525,
      "firstPaint": 525,
      "lastAnalyzed": "2025-12-09T11:14:37.604Z",
      "previousPerformanceScore": 90
    },
    {
      "url": "https://gitechnolo.github.io/biotechproject/Capelli-semplice.html",
      "label": "Capelli (versione semplificata)",
      "slug": "capelli-semplice",
      "category": "accessibilità",
      "performanceScore": 100,
      "loadTime": 516,
      "firstPaint": 516,
      "lastAnalyzed": "2025-12-09T11:14:58.493Z",
      "previousPerformanceScore": 100
    },
    {
      "url": "https://gitechnolo.github.io/biotechproject/Staff.html",
      "label": "Staff",
      "slug": "staff",
      "category": "staff",
      "performanceScore": 100,
      "loadTime": 369,
      "firstPaint": 369,
      "lastAnalyzed": "2025-12-09T11:15:18.765Z",
      "previousPerformanceScore": 100
    },
    {
      "url": "https://gitechnolo.github.io/biotechproject/Progetti.html",
      "label": "Progetti",
      "slug": "progetti",
      "category": "altro",
      "performanceScore": 100,
      "loadTime": 383,
      "firstPaint": 383,
      "lastAnalyzed": "2025-12-09T11:15:39.637Z",
      "previousPerformanceScore": 100
    },
    {
      "url": "https://gitechnolo.github.io/biotechproject/Marketing.html",
      "label": "Marketing",
      "slug": "marketing",
      "category": "mercato cibernetica",
      "performanceScore": 100,
      "loadTime": 750,
      "firstPaint": 323,
      "lastAnalyzed": "2025-12-09T11:15:59.763Z",
      "previousPerformanceScore": 100
    },
    {
      "url": "https://gitechnolo.github.io/biotechproject/O.S_support.html",
      "label": "Supporto OS",
      "slug": "os-support",
      "category": "supporto",
      "performanceScore": 100,
      "loadTime": 527,
      "firstPaint": 227,
      "lastAnalyzed": "2025-12-09T11:16:19.339Z",
      "previousPerformanceScore": 100
    },
    {
      "url": "https://gitechnolo.github.io/biotechproject/Tablet_forum.html",
      "label": "Forum Tablet",
      "slug": "tablet-forum",
      "category": "forum",
      "performanceScore": 100,
      "loadTime": 201,
      "firstPaint": 201,
      "lastAnalyzed": "2025-12-09T11:16:36.985Z",
      "previousPerformanceScore": 100
    },
    {
      "url": "https://gitechnolo.github.io/biotechproject/Specials.html",
      "label": "Specials",
      "slug": "specials",
      "category": "cellule staminali robotica",
      "performanceScore": 100,
      "loadTime": 398,
      "firstPaint": 398,
      "lastAnalyzed": "2025-12-09T11:16:57.812Z",
      "previousPerformanceScore": 100
    },
    {
      "url": "https://gitechnolo.github.io/biotechproject/Tech_Maturity.html",
      "label": "Maturità tecnologica",
      "slug": "tech-maturity",
      "category": "maturità tecnologica",
      "performanceScore": 82,
      "loadTime": 413,
      "firstPaint": 413,
      "lastAnalyzed": "2025-12-09T11:17:19.848Z",
      "previousPerformanceScore": 88
    },
    {
      "url": "https://gitechnolo.github.io/biotechproject/accessibility-it.html",
      "label": "Accessibilità (informazioni)",
      "slug": "accessibility-it",
      "category": "accessibilità",
      "performanceScore": 100,
      "loadTime": 499,
      "firstPaint": 499,
      "lastAnalyzed": "2025-12-09T11:17:39.845Z",
      "previousPerformanceScore": 100
    },
    {
      "url": "https://gitechnolo.github.io/biotechproject/accessibility-en.html",
      "label": "Accessibility (information)",
      "slug": "accessibility-en",
      "category": "accessibilità",
      "performanceScore": 100,
      "loadTime": 379,
      "firstPaint": 379,
      "lastAnalyzed": "2025-12-09T11:17:59.922Z",
      "previousPerformanceScore": 100
    }
  ]
}