{
  "lastUpdated": "2025-10-06T16:36:10.408Z",
  "summary": {
    "totalPages": 24,
    "analyzed": 24,
    "failed": 0,
    "averagePerformance": 97
  },
  "pages": [
    {
      "url": "https://gitechnolo.github.io/biotechproject/index.html",
      "label": "Homepage",
      "slug": "index",
      "category": "biotecnologie",
      "performanceScore": 86,
      "loadTime": 1050,
      "firstPaint": 1050,
      "lastAnalyzed": "2025-10-06T16:27:47.909Z",
      "previousPerformanceScore": 82
    },
    {
      "url": "https://gitechnolo.github.io/biotechproject/Cuore.html",
      "label": "Cuore",
      "slug": "cuore",
      "category": "fisiologia",
      "performanceScore": 99,
      "loadTime": 778,
      "firstPaint": 430,
      "lastAnalyzed": "2025-10-06T16:28:09.845Z",
      "previousPerformanceScore": 99
    },
    {
      "url": "https://gitechnolo.github.io/biotechproject/Cuore-semplice.html",
      "label": "Cuore (versione semplificata)",
      "slug": "cuore-semplice",
      "category": "accessibilità",
      "performanceScore": 100,
      "loadTime": 330,
      "firstPaint": 330,
      "lastAnalyzed": "2025-10-06T16:28:31.626Z",
      "previousPerformanceScore": 100
    },
    {
      "url": "https://gitechnolo.github.io/biotechproject/Apparato_respiratorio.html",
      "label": "Apparato respiratorio",
      "slug": "apparato-respiratorio",
      "category": "fisiologia",
      "performanceScore": 91,
      "loadTime": 444,
      "firstPaint": 306,
      "lastAnalyzed": "2025-10-06T16:28:54.183Z",
      "previousPerformanceScore": 100
    },
    {
      "url": "https://gitechnolo.github.io/biotechproject/Apparato_respiratorio-semplice.html",
      "label": "Apparato respiratorio (versione semplificata)",
      "slug": "apparato-respiratorio-semplice",
      "category": "accessibilità",
      "performanceScore": 100,
      "loadTime": 316,
      "firstPaint": 316,
      "lastAnalyzed": "2025-10-06T16:29:16.132Z",
      "previousPerformanceScore": 100
    },
    {
      "url": "https://gitechnolo.github.io/biotechproject/Apparato_digerente.html",
      "label": "Apparato digerente",
      "slug": "apparato-digerente",
      "category": "fisiologia",
      "performanceScore": 95,
      "loadTime": 910,
      "firstPaint": 318,
      "lastAnalyzed": "2025-10-06T16:29:38.659Z",
      "previousPerformanceScore": 100
    },
    {
      "url": "https://gitechnolo.github.io/biotechproject/Apparato_digerente-semplice.html",
      "label": "Apparato digerente (versione semplificata)",
      "slug": "apparato-digerente-semplice",
      "category": "accessibilità",
      "performanceScore": 94,
      "loadTime": 303,
      "firstPaint": 303,
      "lastAnalyzed": "2025-10-06T16:30:02.932Z",
      "previousPerformanceScore": 98
    },
    {
      "url": "https://gitechnolo.github.io/biotechproject/Apparato_tegumentario.html",
      "label": "Apparato tegumentario",
      "slug": "apparato-tegumentario",
      "category": "fisiologia",
      "performanceScore": 100,
      "loadTime": 346,
      "firstPaint": 346,
      "lastAnalyzed": "2025-10-06T16:30:26.792Z",
      "previousPerformanceScore": 100
    },
    {
      "url": "https://gitechnolo.github.io/biotechproject/Apparato_tegumentario-semplice.html",
      "label": "Apparato tegumentario (versione semplificata)",
      "slug": "apparato-tegumentario-semplice",
      "category": "accessibilità",
      "performanceScore": 92,
      "loadTime": 452,
      "firstPaint": 452,
      "lastAnalyzed": "2025-10-06T16:30:50.520Z",
      "previousPerformanceScore": 97
    },
    {
      "url": "https://gitechnolo.github.io/biotechproject/Sistema_linfatico.html",
      "label": "Sistema linfatico",
      "slug": "sistema-linfatico",
      "category": "fisiologia",
      "performanceScore": 100,
      "loadTime": 391,
      "firstPaint": 391,
      "lastAnalyzed": "2025-10-06T16:31:12.639Z",
      "previousPerformanceScore": 100
    },
    {
      "url": "https://gitechnolo.github.io/biotechproject/Sistema_linfatico-semplice.html",
      "label": "Sistema linfatico (versione semplificata)",
      "slug": "sistema-linfatico-semplice",
      "category": "accessibilità",
      "performanceScore": 100,
      "loadTime": 331,
      "firstPaint": 331,
      "lastAnalyzed": "2025-10-06T16:31:34.249Z",
      "previousPerformanceScore": 100
    },
    {
      "url": "https://gitechnolo.github.io/biotechproject/Dermatologia.html",
      "label": "Dermatologia",
      "slug": "dermatologia",
      "category": "fisiologia",
      "performanceScore": 100,
      "loadTime": 391,
      "firstPaint": 391,
      "lastAnalyzed": "2025-10-06T16:31:56.046Z",
      "previousPerformanceScore": 100
    },
    {
      "url": "https://gitechnolo.github.io/biotechproject/Dermatologia-semplice.html",
      "label": "Dermatologia (versione semplificata)",
      "slug": "dermatologia-semplice",
      "category": "accessibilità",
      "performanceScore": 100,
      "loadTime": 706,
      "firstPaint": 333,
      "lastAnalyzed": "2025-10-06T16:32:18.371Z",
      "previousPerformanceScore": 100
    },
    {
      "url": "https://gitechnolo.github.io/biotechproject/Cellula.html",
      "label": "Cellula",
      "slug": "cellula",
      "category": "fisiologia",
      "performanceScore": 98,
      "loadTime": 1003,
      "firstPaint": 346,
      "lastAnalyzed": "2025-10-06T16:32:40.924Z",
      "previousPerformanceScore": 99
    },
    {
      "url": "https://gitechnolo.github.io/biotechproject/Cellula-semplice.html",
      "label": "Cellula (versione semplificata)",
      "slug": "cellula-semplice",
      "category": "accessibilità",
      "performanceScore": 100,
      "loadTime": 354,
      "firstPaint": 354,
      "lastAnalyzed": "2025-10-06T16:33:02.591Z",
      "previousPerformanceScore": 100
    },
    {
      "url": "https://gitechnolo.github.io/biotechproject/Staff.html",
      "label": "Staff",
      "slug": "staff",
      "category": "staff",
      "performanceScore": 99,
      "loadTime": 993,
      "firstPaint": 322,
      "lastAnalyzed": "2025-10-06T16:33:23.248Z",
      "previousPerformanceScore": 100
    },
    {
      "url": "https://gitechnolo.github.io/biotechproject/Progetti.html",
      "label": "Progetti",
      "slug": "progetti",
      "category": "altro",
      "performanceScore": 100,
      "loadTime": 317,
      "firstPaint": 317,
      "lastAnalyzed": "2025-10-06T16:33:44.023Z",
      "previousPerformanceScore": 100
    },
    {
      "url": "https://gitechnolo.github.io/biotechproject/Marketing.html",
      "label": "Marketing",
      "slug": "marketing",
      "category": "mercato cibernetica",
      "performanceScore": 99,
      "loadTime": 900,
      "firstPaint": 363,
      "lastAnalyzed": "2025-10-06T16:34:04.437Z",
      "previousPerformanceScore": 100
    },
    {
      "url": "https://gitechnolo.github.io/biotechproject/O.S_support.html",
      "label": "Supporto OS",
      "slug": "os-support",
      "category": "supporto",
      "performanceScore": 100,
      "loadTime": 182,
      "firstPaint": 182,
      "lastAnalyzed": "2025-10-06T16:34:24.928Z",
      "previousPerformanceScore": 100
    },
    {
      "url": "https://gitechnolo.github.io/biotechproject/Tablet_forum.html",
      "label": "Forum Tablet",
      "slug": "tablet-forum",
      "category": "forum",
      "performanceScore": 100,
      "loadTime": 187,
      "firstPaint": 187,
      "lastAnalyzed": "2025-10-06T16:34:43.311Z",
      "previousPerformanceScore": 100
    },
    {
      "url": "https://gitechnolo.github.io/biotechproject/Specials.html",
      "label": "Specials",
      "slug": "specials",
      "category": "cellule staminali robotica",
      "performanceScore": 100,
      "loadTime": 329,
      "firstPaint": 329,
      "lastAnalyzed": "2025-10-06T16:35:04.023Z",
      "previousPerformanceScore": 100
    },
    {
      "url": "https://gitechnolo.github.io/biotechproject/Tech_Maturity.html",
      "label": "Maturità tecnologica",
      "slug": "tech-maturity",
      "category": "maturità tecnologica",
      "performanceScore": 85,
      "loadTime": 358,
      "firstPaint": 358,
      "lastAnalyzed": "2025-10-06T16:35:25.897Z",
      "previousPerformanceScore": 98
    },
    {
      "url": "https://gitechnolo.github.io/biotechproject/accessibility-it.html",
      "label": "Accessibilità (informazioni)",
      "slug": "accessibility-it",
      "category": "accessibilità",
      "performanceScore": 100,
      "loadTime": 626,
      "firstPaint": 347,
      "lastAnalyzed": "2025-10-06T16:35:46.907Z",
      "previousPerformanceScore": 100
    },
    {
      "url": "https://gitechnolo.github.io/biotechproject/accessibility-en.html",
      "label": "Accessibility (information)",
      "slug": "accessibility-en",
      "category": "accessibilità",
      "performanceScore": 99,
      "loadTime": 947,
      "firstPaint": 335,
      "lastAnalyzed": "2025-10-06T16:36:07.380Z",
      "previousPerformanceScore": 99
    }
  ]
}