{
  "lastUpdated": "2025-10-26T11:20:19.634Z",
  "summary": {
    "totalPages": 26,
    "analyzed": 26,
    "failed": 0,
    "averagePerformance": 97
  },
  "pages": [
    {
      "url": "https://gitechnolo.github.io/biotechproject/index.html",
      "label": "Homepage",
      "slug": "index",
      "category": "biotecnologie",
      "performanceScore": 87,
      "loadTime": 1064,
      "firstPaint": 1064,
      "lastAnalyzed": "2025-10-26T11:11:13.909Z",
      "previousPerformanceScore": 73
    },
    {
      "url": "https://gitechnolo.github.io/biotechproject/Cuore.html",
      "label": "Cuore",
      "slug": "cuore",
      "category": "fisiologia",
      "performanceScore": 99,
      "loadTime": 916,
      "firstPaint": 385,
      "lastAnalyzed": "2025-10-26T11:11:35.679Z",
      "previousPerformanceScore": 100
    },
    {
      "url": "https://gitechnolo.github.io/biotechproject/Cuore-semplice.html",
      "label": "Cuore (versione semplificata)",
      "slug": "cuore-semplice",
      "category": "accessibilità",
      "performanceScore": 100,
      "loadTime": 290,
      "firstPaint": 290,
      "lastAnalyzed": "2025-10-26T11:11:57.471Z",
      "previousPerformanceScore": 100
    },
    {
      "url": "https://gitechnolo.github.io/biotechproject/Apparato_respiratorio.html",
      "label": "Apparato respiratorio",
      "slug": "apparato-respiratorio",
      "category": "fisiologia",
      "performanceScore": 100,
      "loadTime": 275,
      "firstPaint": 275,
      "lastAnalyzed": "2025-10-26T11:12:19.426Z",
      "previousPerformanceScore": 100
    },
    {
      "url": "https://gitechnolo.github.io/biotechproject/Apparato_respiratorio-semplice.html",
      "label": "Apparato respiratorio (versione semplificata)",
      "slug": "apparato-respiratorio-semplice",
      "category": "accessibilità",
      "performanceScore": 100,
      "loadTime": 278,
      "firstPaint": 278,
      "lastAnalyzed": "2025-10-26T11:12:41.322Z",
      "previousPerformanceScore": 100
    },
    {
      "url": "https://gitechnolo.github.io/biotechproject/Apparato_digerente.html",
      "label": "Apparato digerente",
      "slug": "apparato-digerente",
      "category": "fisiologia",
      "performanceScore": 98,
      "loadTime": 1008,
      "firstPaint": 280,
      "lastAnalyzed": "2025-10-26T11:13:03.765Z",
      "previousPerformanceScore": 95
    },
    {
      "url": "https://gitechnolo.github.io/biotechproject/Apparato_digerente-semplice.html",
      "label": "Apparato digerente (versione semplificata)",
      "slug": "apparato-digerente-semplice",
      "category": "accessibilità",
      "performanceScore": 90,
      "loadTime": 1100,
      "firstPaint": 273,
      "lastAnalyzed": "2025-10-26T11:13:28.210Z",
      "previousPerformanceScore": 93
    },
    {
      "url": "https://gitechnolo.github.io/biotechproject/Apparato_tegumentario.html",
      "label": "Apparato tegumentario",
      "slug": "apparato-tegumentario",
      "category": "fisiologia",
      "performanceScore": 100,
      "loadTime": 287,
      "firstPaint": 287,
      "lastAnalyzed": "2025-10-26T11:13:51.769Z",
      "previousPerformanceScore": 100
    },
    {
      "url": "https://gitechnolo.github.io/biotechproject/Apparato_tegumentario-semplice.html",
      "label": "Apparato tegumentario (versione semplificata)",
      "slug": "apparato-tegumentario-semplice",
      "category": "accessibilità",
      "performanceScore": 91,
      "loadTime": 293,
      "firstPaint": 293,
      "lastAnalyzed": "2025-10-26T11:14:15.638Z",
      "previousPerformanceScore": 93
    },
    {
      "url": "https://gitechnolo.github.io/biotechproject/Sistema_linfatico.html",
      "label": "Sistema linfatico",
      "slug": "sistema-linfatico",
      "category": "fisiologia",
      "performanceScore": 100,
      "loadTime": 294,
      "firstPaint": 294,
      "lastAnalyzed": "2025-10-26T11:14:36.678Z",
      "previousPerformanceScore": 100
    },
    {
      "url": "https://gitechnolo.github.io/biotechproject/Sistema_linfatico-semplice.html",
      "label": "Sistema linfatico (versione semplificata)",
      "slug": "sistema-linfatico-semplice",
      "category": "accessibilità",
      "performanceScore": 100,
      "loadTime": 283,
      "firstPaint": 283,
      "lastAnalyzed": "2025-10-26T11:14:58.322Z",
      "previousPerformanceScore": 100
    },
    {
      "url": "https://gitechnolo.github.io/biotechproject/Dermatologia.html",
      "label": "Dermatologia",
      "slug": "dermatologia",
      "category": "fisiologia",
      "performanceScore": 100,
      "loadTime": 273,
      "firstPaint": 273,
      "lastAnalyzed": "2025-10-26T11:15:19.935Z",
      "previousPerformanceScore": 100
    },
    {
      "url": "https://gitechnolo.github.io/biotechproject/Dermatologia-semplice.html",
      "label": "Dermatologia (versione semplificata)",
      "slug": "dermatologia-semplice",
      "category": "accessibilità",
      "performanceScore": 100,
      "loadTime": 644,
      "firstPaint": 280,
      "lastAnalyzed": "2025-10-26T11:15:42.281Z",
      "previousPerformanceScore": 100
    },
    {
      "url": "https://gitechnolo.github.io/biotechproject/Cellula.html",
      "label": "Cellula",
      "slug": "cellula",
      "category": "fisiologia",
      "performanceScore": 95,
      "loadTime": 1142,
      "firstPaint": 358,
      "lastAnalyzed": "2025-10-26T11:16:05.111Z",
      "previousPerformanceScore": 92
    },
    {
      "url": "https://gitechnolo.github.io/biotechproject/Cellula-semplice.html",
      "label": "Cellula (versione semplificata)",
      "slug": "cellula-semplice",
      "category": "accessibilità",
      "performanceScore": 100,
      "loadTime": 266,
      "firstPaint": 266,
      "lastAnalyzed": "2025-10-26T11:16:26.544Z",
      "previousPerformanceScore": 100
    },
    {
      "url": "https://gitechnolo.github.io/biotechproject/Capelli.html",
      "label": "Capelli",
      "slug": "capelli",
      "category": "fisiologia",
      "performanceScore": 88,
      "loadTime": 621,
      "firstPaint": 621,
      "lastAnalyzed": "2025-10-26T11:16:50.895Z",
      "previousPerformanceScore": 75
    },
    {
      "url": "https://gitechnolo.github.io/biotechproject/Capelli-semplice.html",
      "label": "Capelli (versione semplificata)",
      "slug": "capelli-semplice",
      "category": "accessibilità",
      "performanceScore": 100,
      "loadTime": 292,
      "firstPaint": 292,
      "lastAnalyzed": "2025-10-26T11:17:12.081Z",
      "previousPerformanceScore": 100
    },
    {
      "url": "https://gitechnolo.github.io/biotechproject/Staff.html",
      "label": "Staff",
      "slug": "staff",
      "category": "staff",
      "performanceScore": 100,
      "loadTime": 812,
      "firstPaint": 241,
      "lastAnalyzed": "2025-10-26T11:17:32.583Z",
      "previousPerformanceScore": 100
    },
    {
      "url": "https://gitechnolo.github.io/biotechproject/Progetti.html",
      "label": "Progetti",
      "slug": "progetti",
      "category": "altro",
      "performanceScore": 100,
      "loadTime": 605,
      "firstPaint": 236,
      "lastAnalyzed": "2025-10-26T11:17:53.308Z",
      "previousPerformanceScore": 100
    },
    {
      "url": "https://gitechnolo.github.io/biotechproject/Marketing.html",
      "label": "Marketing",
      "slug": "marketing",
      "category": "mercato cibernetica",
      "performanceScore": 100,
      "loadTime": 785,
      "firstPaint": 245,
      "lastAnalyzed": "2025-10-26T11:18:13.307Z",
      "previousPerformanceScore": 100
    },
    {
      "url": "https://gitechnolo.github.io/biotechproject/O.S_support.html",
      "label": "Supporto OS",
      "slug": "os-support",
      "category": "supporto",
      "performanceScore": 100,
      "loadTime": 427,
      "firstPaint": 250,
      "lastAnalyzed": "2025-10-26T11:18:33.925Z",
      "previousPerformanceScore": 100
    },
    {
      "url": "https://gitechnolo.github.io/biotechproject/Tablet_forum.html",
      "label": "Forum Tablet",
      "slug": "tablet-forum",
      "category": "forum",
      "performanceScore": 100,
      "loadTime": 147,
      "firstPaint": 147,
      "lastAnalyzed": "2025-10-26T11:18:52.578Z",
      "previousPerformanceScore": 100
    },
    {
      "url": "https://gitechnolo.github.io/biotechproject/Specials.html",
      "label": "Specials",
      "slug": "specials",
      "category": "cellule staminali robotica",
      "performanceScore": 100,
      "loadTime": 235,
      "firstPaint": 235,
      "lastAnalyzed": "2025-10-26T11:19:13.203Z",
      "previousPerformanceScore": 100
    },
    {
      "url": "https://gitechnolo.github.io/biotechproject/Tech_Maturity.html",
      "label": "Maturità tecnologica",
      "slug": "tech-maturity",
      "category": "maturità tecnologica",
      "performanceScore": 83,
      "loadTime": 266,
      "firstPaint": 266,
      "lastAnalyzed": "2025-10-26T11:19:35.620Z",
      "previousPerformanceScore": 86
    },
    {
      "url": "https://gitechnolo.github.io/biotechproject/accessibility-it.html",
      "label": "Accessibilità (informazioni)",
      "slug": "accessibility-it",
      "category": "accessibilità",
      "performanceScore": 100,
      "loadTime": 739,
      "firstPaint": 271,
      "lastAnalyzed": "2025-10-26T11:19:56.036Z",
      "previousPerformanceScore": 100
    },
    {
      "url": "https://gitechnolo.github.io/biotechproject/accessibility-en.html",
      "label": "Accessibility (information)",
      "slug": "accessibility-en",
      "category": "accessibilità",
      "performanceScore": 99,
      "loadTime": 860,
      "firstPaint": 359,
      "lastAnalyzed": "2025-10-26T11:20:16.611Z",
      "previousPerformanceScore": 99
    }
  ]
}