{
  "lastUpdated": "2026-04-06T22:06:11.642Z",
  "summary": {
    "totalPages": 26,
    "analyzed": 26,
    "failed": 0,
    "averagePerformance": 93,
    "stressTest": {
      "simulatedUsers": 5000,
      "methodology": "Logarithmic Load Degradation (SRE 2026)",
      "globalResilienceScore": 85,
      "status": "STABLE / HIGH_AVAILABILITY"
    }
  },
  "pages": [
    {
      "url": "https://gitechnolo.github.io/biotechproject/index.html",
      "label": "Homepage",
      "slug": "index",
      "category": "biotecnologie",
      "performanceScore": 90,
      "loadTime": 2119,
      "firstPaint": 1766,
      "lastAnalyzed": "2026-04-06T22:01:37.036Z",
      "stressResilienceScore": 82,
      "previousPerformanceScore": 91
    },
    {
      "url": "https://gitechnolo.github.io/biotechproject/Cuore.html",
      "label": "Cuore",
      "slug": "cuore",
      "category": "fisiologia",
      "performanceScore": 96,
      "loadTime": 2668,
      "firstPaint": 1129,
      "lastAnalyzed": "2026-04-06T22:01:47.656Z",
      "stressResilienceScore": 87,
      "previousPerformanceScore": 96
    },
    {
      "url": "https://gitechnolo.github.io/biotechproject/Cuore-semplice.html",
      "label": "Cuore (versione semplificata)",
      "slug": "cuore-semplice",
      "category": "accessibilità",
      "performanceScore": 97,
      "loadTime": 2480,
      "firstPaint": 1489,
      "lastAnalyzed": "2026-04-06T22:01:58.372Z",
      "stressResilienceScore": 88,
      "previousPerformanceScore": 92
    },
    {
      "url": "https://gitechnolo.github.io/biotechproject/Apparato_respiratorio.html",
      "label": "Apparato respiratorio",
      "slug": "apparato-respiratorio",
      "category": "fisiologia",
      "performanceScore": 88,
      "loadTime": 3872,
      "firstPaint": 1125,
      "lastAnalyzed": "2026-04-06T22:02:09.337Z",
      "stressResilienceScore": 80,
      "previousPerformanceScore": 87
    },
    {
      "url": "https://gitechnolo.github.io/biotechproject/Apparato_respiratorio-semplice.html",
      "label": "Apparato respiratorio (versione semplificata)",
      "slug": "apparato-respiratorio-semplice",
      "category": "accessibilità",
      "performanceScore": 85,
      "loadTime": 3698,
      "firstPaint": 1168,
      "lastAnalyzed": "2026-04-06T22:02:20.216Z",
      "stressResilienceScore": 77,
      "previousPerformanceScore": 85
    },
    {
      "url": "https://gitechnolo.github.io/biotechproject/Apparato_digerente.html",
      "label": "Apparato digerente",
      "slug": "apparato-digerente",
      "category": "fisiologia",
      "performanceScore": 87,
      "loadTime": 3613,
      "firstPaint": 1419,
      "lastAnalyzed": "2026-04-06T22:02:31.968Z",
      "stressResilienceScore": 79,
      "previousPerformanceScore": 83
    },
    {
      "url": "https://gitechnolo.github.io/biotechproject/Apparato_digerente-semplice.html",
      "label": "Apparato digerente (versione semplificata)",
      "slug": "apparato-digerente-semplice",
      "category": "accessibilità",
      "performanceScore": 86,
      "loadTime": 3125,
      "firstPaint": 985,
      "lastAnalyzed": "2026-04-06T22:02:44.018Z",
      "stressResilienceScore": 78,
      "previousPerformanceScore": 82
    },
    {
      "url": "https://gitechnolo.github.io/biotechproject/Apparato_tegumentario.html",
      "label": "Apparato tegumentario",
      "slug": "apparato-tegumentario",
      "category": "fisiologia",
      "performanceScore": 89,
      "loadTime": 2774,
      "firstPaint": 1256,
      "lastAnalyzed": "2026-04-06T22:02:55.590Z",
      "stressResilienceScore": 81,
      "previousPerformanceScore": 93
    },
    {
      "url": "https://gitechnolo.github.io/biotechproject/Apparato_tegumentario-semplice.html",
      "label": "Apparato tegumentario (versione semplificata)",
      "slug": "apparato-tegumentario-semplice",
      "category": "accessibilità",
      "performanceScore": 89,
      "loadTime": 3574,
      "firstPaint": 1734,
      "lastAnalyzed": "2026-04-06T22:03:07.181Z",
      "stressResilienceScore": 81,
      "previousPerformanceScore": 90
    },
    {
      "url": "https://gitechnolo.github.io/biotechproject/Sistema_linfatico.html",
      "label": "Sistema linfatico",
      "slug": "sistema-linfatico",
      "category": "fisiologia",
      "performanceScore": 96,
      "loadTime": 2673,
      "firstPaint": 1128,
      "lastAnalyzed": "2026-04-06T22:03:17.895Z",
      "stressResilienceScore": 87,
      "previousPerformanceScore": 97
    },
    {
      "url": "https://gitechnolo.github.io/biotechproject/Sistema_linfatico-semplice.html",
      "label": "Sistema linfatico (versione semplificata)",
      "slug": "sistema-linfatico-semplice",
      "category": "accessibilità",
      "performanceScore": 93,
      "loadTime": 3040,
      "firstPaint": 1573,
      "lastAnalyzed": "2026-04-06T22:03:28.617Z",
      "stressResilienceScore": 85,
      "previousPerformanceScore": 97
    },
    {
      "url": "https://gitechnolo.github.io/biotechproject/Dermatologia.html",
      "label": "Dermatologia",
      "slug": "dermatologia",
      "category": "fisiologia",
      "performanceScore": 98,
      "loadTime": 2404,
      "firstPaint": 1109,
      "lastAnalyzed": "2026-04-06T22:03:39.383Z",
      "stressResilienceScore": 89,
      "previousPerformanceScore": 99
    },
    {
      "url": "https://gitechnolo.github.io/biotechproject/Dermatologia-semplice.html",
      "label": "Dermatologia (versione semplificata)",
      "slug": "dermatologia-semplice",
      "category": "accessibilità",
      "performanceScore": 97,
      "loadTime": 2438,
      "firstPaint": 1586,
      "lastAnalyzed": "2026-04-06T22:03:50.208Z",
      "stressResilienceScore": 88,
      "previousPerformanceScore": 96
    },
    {
      "url": "https://gitechnolo.github.io/biotechproject/Cellula.html",
      "label": "Cellula",
      "slug": "cellula",
      "category": "fisiologia",
      "performanceScore": 91,
      "loadTime": 3384,
      "firstPaint": 1300,
      "lastAnalyzed": "2026-04-06T22:04:01.800Z",
      "stressResilienceScore": 83,
      "previousPerformanceScore": 86
    },
    {
      "url": "https://gitechnolo.github.io/biotechproject/Cellula-semplice.html",
      "label": "Cellula (versione semplificata)",
      "slug": "cellula-semplice",
      "category": "accessibilità",
      "performanceScore": 87,
      "loadTime": 3941,
      "firstPaint": 1725,
      "lastAnalyzed": "2026-04-06T22:04:12.177Z",
      "stressResilienceScore": 79,
      "previousPerformanceScore": 90
    },
    {
      "url": "https://gitechnolo.github.io/biotechproject/Capelli.html",
      "label": "Capelli",
      "slug": "capelli",
      "category": "fisiologia",
      "performanceScore": 93,
      "loadTime": 2068,
      "firstPaint": 1281,
      "lastAnalyzed": "2026-04-06T22:04:24.721Z",
      "stressResilienceScore": 85,
      "previousPerformanceScore": 96
    },
    {
      "url": "https://gitechnolo.github.io/biotechproject/Capelli-semplice.html",
      "label": "Capelli (versione semplificata)",
      "slug": "capelli-semplice",
      "category": "accessibilità",
      "performanceScore": 98,
      "loadTime": 2254,
      "firstPaint": 1562,
      "lastAnalyzed": "2026-04-06T22:04:35.223Z",
      "stressResilienceScore": 89,
      "previousPerformanceScore": 97
    },
    {
      "url": "https://gitechnolo.github.io/biotechproject/Staff.html",
      "label": "Staff",
      "slug": "staff",
      "category": "staff",
      "performanceScore": 99,
      "loadTime": 2121,
      "firstPaint": 1205,
      "lastAnalyzed": "2026-04-06T22:04:45.670Z",
      "stressResilienceScore": 90,
      "previousPerformanceScore": 98
    },
    {
      "url": "https://gitechnolo.github.io/biotechproject/Progetti.html",
      "label": "Progetti",
      "slug": "progetti",
      "category": "altro",
      "performanceScore": 98,
      "loadTime": 2347,
      "firstPaint": 1056,
      "lastAnalyzed": "2026-04-06T22:04:56.074Z",
      "stressResilienceScore": 89,
      "previousPerformanceScore": 98
    },
    {
      "url": "https://gitechnolo.github.io/biotechproject/Marketing.html",
      "label": "Marketing",
      "slug": "marketing",
      "category": "mercato cibernetica",
      "performanceScore": 99,
      "loadTime": 2034,
      "firstPaint": 1115,
      "lastAnalyzed": "2026-04-06T22:05:06.315Z",
      "stressResilienceScore": 90,
      "previousPerformanceScore": 99
    },
    {
      "url": "https://gitechnolo.github.io/biotechproject/O.S_support.html",
      "label": "Supporto OS",
      "slug": "os-support",
      "category": "supporto",
      "performanceScore": 100,
      "loadTime": 1805,
      "firstPaint": 756,
      "lastAnalyzed": "2026-04-06T22:05:15.689Z",
      "stressResilienceScore": 91,
      "previousPerformanceScore": 100
    },
    {
      "url": "https://gitechnolo.github.io/biotechproject/Tablet_forum.html",
      "label": "Forum Tablet",
      "slug": "tablet-forum",
      "category": "forum",
      "performanceScore": 86,
      "loadTime": 755,
      "firstPaint": 755,
      "lastAnalyzed": "2026-04-06T22:05:24.849Z",
      "stressResilienceScore": 78,
      "previousPerformanceScore": 100
    },
    {
      "url": "https://gitechnolo.github.io/biotechproject/Specials.html",
      "label": "Specials",
      "slug": "specials",
      "category": "cellule staminali robotica",
      "performanceScore": 98,
      "loadTime": 2338,
      "firstPaint": 1118,
      "lastAnalyzed": "2026-04-06T22:05:35.151Z",
      "stressResilienceScore": 89,
      "previousPerformanceScore": 99
    },
    {
      "url": "https://gitechnolo.github.io/biotechproject/Tech_Maturity.html",
      "label": "Maturità tecnologica",
      "slug": "tech-maturity",
      "category": "maturità tecnologica",
      "performanceScore": 86,
      "loadTime": 2715,
      "firstPaint": 838,
      "lastAnalyzed": "2026-04-06T22:05:48.287Z",
      "stressResilienceScore": 78,
      "previousPerformanceScore": 84
    },
    {
      "url": "https://gitechnolo.github.io/biotechproject/accessibility-it.html",
      "label": "Accessibilità (informazioni)",
      "slug": "accessibility-it",
      "category": "accessibilità",
      "performanceScore": 98,
      "loadTime": 2341,
      "firstPaint": 1101,
      "lastAnalyzed": "2026-04-06T22:05:58.501Z",
      "stressResilienceScore": 89,
      "previousPerformanceScore": 98
    },
    {
      "url": "https://gitechnolo.github.io/biotechproject/accessibility-en.html",
      "label": "Accessibility (information)",
      "slug": "accessibility-en",
      "category": "accessibilità",
      "performanceScore": 98,
      "loadTime": 2343,
      "firstPaint": 1113,
      "lastAnalyzed": "2026-04-06T22:06:08.613Z",
      "stressResilienceScore": 89,
      "previousPerformanceScore": 98
    }
  ]
}