{
  "lastUpdated": "2025-09-25T15:58:59.049Z",
  "summary": {
    "totalPages": 24,
    "analyzed": 24,
    "failed": 0,
    "averagePerformance": 97
  },
  "pages": [
    {
      "url": "https://gitechnolo.github.io/biotechproject/index.html",
      "label": "Homepage",
      "slug": "index",
      "category": "biotecnologie",
      "performanceScore": 72,
      "loadTime": 1835,
      "firstPaint": 826,
      "lastAnalyzed": "2025-09-25T15:50:40.331Z",
      "previousPerformanceScore": 79
    },
    {
      "url": "https://gitechnolo.github.io/biotechproject/Cuore.html",
      "label": "Cuore",
      "slug": "cuore",
      "category": "fisiologia",
      "performanceScore": 99,
      "loadTime": 936,
      "firstPaint": 390,
      "lastAnalyzed": "2025-09-25T15:51:02.201Z",
      "previousPerformanceScore": 99
    },
    {
      "url": "https://gitechnolo.github.io/biotechproject/Cuore-semplice.html",
      "label": "Cuore (versione semplificata)",
      "slug": "cuore-semplice",
      "category": "accessibilità",
      "performanceScore": 100,
      "loadTime": 309,
      "firstPaint": 309,
      "lastAnalyzed": "2025-09-25T15:51:23.946Z",
      "previousPerformanceScore": 100
    },
    {
      "url": "https://gitechnolo.github.io/biotechproject/Apparato_respiratorio.html",
      "label": "Apparato respiratorio",
      "slug": "apparato-respiratorio",
      "category": "fisiologia",
      "performanceScore": 100,
      "loadTime": 363,
      "firstPaint": 363,
      "lastAnalyzed": "2025-09-25T15:51:45.756Z",
      "previousPerformanceScore": 100
    },
    {
      "url": "https://gitechnolo.github.io/biotechproject/Apparato_respiratorio-semplice.html",
      "label": "Apparato respiratorio (versione semplificata)",
      "slug": "apparato-respiratorio-semplice",
      "category": "accessibilità",
      "performanceScore": 100,
      "loadTime": 410,
      "firstPaint": 410,
      "lastAnalyzed": "2025-09-25T15:52:07.719Z",
      "previousPerformanceScore": 100
    },
    {
      "url": "https://gitechnolo.github.io/biotechproject/Apparato_digerente.html",
      "label": "Apparato digerente",
      "slug": "apparato-digerente",
      "category": "fisiologia",
      "performanceScore": 98,
      "loadTime": 1056,
      "firstPaint": 441,
      "lastAnalyzed": "2025-09-25T15:52:30.069Z",
      "previousPerformanceScore": 100
    },
    {
      "url": "https://gitechnolo.github.io/biotechproject/Apparato_digerente-semplice.html",
      "label": "Apparato digerente (versione semplificata)",
      "slug": "apparato-digerente-semplice",
      "category": "accessibilità",
      "performanceScore": 100,
      "loadTime": 349,
      "firstPaint": 349,
      "lastAnalyzed": "2025-09-25T15:52:54.521Z",
      "previousPerformanceScore": 99
    },
    {
      "url": "https://gitechnolo.github.io/biotechproject/Apparato_tegumentario.html",
      "label": "Apparato tegumentario",
      "slug": "apparato-tegumentario",
      "category": "fisiologia",
      "performanceScore": 87,
      "loadTime": 693,
      "firstPaint": 350,
      "lastAnalyzed": "2025-09-25T15:53:18.172Z",
      "previousPerformanceScore": 100
    },
    {
      "url": "https://gitechnolo.github.io/biotechproject/Apparato_tegumentario-semplice.html",
      "label": "Apparato tegumentario (versione semplificata)",
      "slug": "apparato-tegumentario-semplice",
      "category": "accessibilità",
      "performanceScore": 100,
      "loadTime": 349,
      "firstPaint": 349,
      "lastAnalyzed": "2025-09-25T15:53:41.736Z",
      "previousPerformanceScore": 97
    },
    {
      "url": "https://gitechnolo.github.io/biotechproject/Sistema_linfatico.html",
      "label": "Sistema linfatico",
      "slug": "sistema-linfatico",
      "category": "fisiologia",
      "performanceScore": 100,
      "loadTime": 378,
      "firstPaint": 378,
      "lastAnalyzed": "2025-09-25T15:54:03.472Z",
      "previousPerformanceScore": 93
    },
    {
      "url": "https://gitechnolo.github.io/biotechproject/Sistema_linfatico-semplice.html",
      "label": "Sistema linfatico (versione semplificata)",
      "slug": "sistema-linfatico-semplice",
      "category": "accessibilità",
      "performanceScore": 100,
      "loadTime": 327,
      "firstPaint": 327,
      "lastAnalyzed": "2025-09-25T15:54:25.389Z",
      "previousPerformanceScore": 100
    },
    {
      "url": "https://gitechnolo.github.io/biotechproject/Dermatologia.html",
      "label": "Dermatologia",
      "slug": "dermatologia",
      "category": "fisiologia",
      "performanceScore": 100,
      "loadTime": 453,
      "firstPaint": 386,
      "lastAnalyzed": "2025-09-25T15:54:46.850Z",
      "previousPerformanceScore": 100
    },
    {
      "url": "https://gitechnolo.github.io/biotechproject/Dermatologia-semplice.html",
      "label": "Dermatologia (versione semplificata)",
      "slug": "dermatologia-semplice",
      "category": "accessibilità",
      "performanceScore": 99,
      "loadTime": 910,
      "firstPaint": 359,
      "lastAnalyzed": "2025-09-25T15:55:09.083Z",
      "previousPerformanceScore": 99
    },
    {
      "url": "https://gitechnolo.github.io/biotechproject/Cellula.html",
      "label": "Cellula",
      "slug": "cellula",
      "category": "fisiologia",
      "performanceScore": 100,
      "loadTime": 426,
      "firstPaint": 426,
      "lastAnalyzed": "2025-09-25T15:55:30.399Z",
      "previousPerformanceScore": 100
    },
    {
      "url": "https://gitechnolo.github.io/biotechproject/Cellula-semplice.html",
      "label": "Cellula (versione semplificata)",
      "slug": "cellula-semplice",
      "category": "accessibilità",
      "performanceScore": 100,
      "loadTime": 371,
      "firstPaint": 371,
      "lastAnalyzed": "2025-09-25T15:55:52.133Z",
      "previousPerformanceScore": 100
    },
    {
      "url": "https://gitechnolo.github.io/biotechproject/Staff.html",
      "label": "Staff",
      "slug": "staff",
      "category": "staff",
      "performanceScore": 99,
      "loadTime": 833,
      "firstPaint": 300,
      "lastAnalyzed": "2025-09-25T15:56:12.583Z",
      "previousPerformanceScore": 99
    },
    {
      "url": "https://gitechnolo.github.io/biotechproject/Progetti.html",
      "label": "Progetti",
      "slug": "progetti",
      "category": "altro",
      "performanceScore": 100,
      "loadTime": 304,
      "firstPaint": 304,
      "lastAnalyzed": "2025-09-25T15:56:33.413Z",
      "previousPerformanceScore": 100
    },
    {
      "url": "https://gitechnolo.github.io/biotechproject/Marketing.html",
      "label": "Marketing",
      "slug": "marketing",
      "category": "mercato cibernetica",
      "performanceScore": 99,
      "loadTime": 939,
      "firstPaint": 329,
      "lastAnalyzed": "2025-09-25T15:56:53.541Z",
      "previousPerformanceScore": 99
    },
    {
      "url": "https://gitechnolo.github.io/biotechproject/O.S_support.html",
      "label": "Supporto OS",
      "slug": "os-support",
      "category": "supporto",
      "performanceScore": 100,
      "loadTime": 226,
      "firstPaint": 226,
      "lastAnalyzed": "2025-09-25T15:57:13.825Z",
      "previousPerformanceScore": 100
    },
    {
      "url": "https://gitechnolo.github.io/biotechproject/Tablet_forum.html",
      "label": "Forum Tablet",
      "slug": "tablet-forum",
      "category": "forum",
      "performanceScore": 100,
      "loadTime": 240,
      "firstPaint": 240,
      "lastAnalyzed": "2025-09-25T15:57:32.208Z",
      "previousPerformanceScore": 100
    },
    {
      "url": "https://gitechnolo.github.io/biotechproject/Specials.html",
      "label": "Specials",
      "slug": "specials",
      "category": "cellule staminali robotica",
      "performanceScore": 100,
      "loadTime": 352,
      "firstPaint": 352,
      "lastAnalyzed": "2025-09-25T15:57:53.070Z",
      "previousPerformanceScore": 100
    },
    {
      "url": "https://gitechnolo.github.io/biotechproject/Tech_Maturity.html",
      "label": "Maturità tecnologica",
      "slug": "tech-maturity",
      "category": "maturità tecnologica",
      "performanceScore": 88,
      "loadTime": 316,
      "firstPaint": 316,
      "lastAnalyzed": "2025-09-25T15:58:14.862Z",
      "previousPerformanceScore": 97
    },
    {
      "url": "https://gitechnolo.github.io/biotechproject/accessibility-it.html",
      "label": "Accessibilità (informazioni)",
      "slug": "accessibility-it",
      "category": "accessibilità",
      "performanceScore": 99,
      "loadTime": 977,
      "firstPaint": 319,
      "lastAnalyzed": "2025-09-25T15:58:35.571Z",
      "previousPerformanceScore": 100
    },
    {
      "url": "https://gitechnolo.github.io/biotechproject/accessibility-en.html",
      "label": "Accessibility (information)",
      "slug": "accessibility-en",
      "category": "accessibilità",
      "performanceScore": 99,
      "loadTime": 964,
      "firstPaint": 376,
      "lastAnalyzed": "2025-09-25T15:58:56.026Z",
      "previousPerformanceScore": 100
    }
  ]
}